odoo/addons/product_assortment/README.rst
odoo/addons/product_assortment/__init__.py
odoo/addons/product_assortment/__manifest__.py
odoo/addons/product_assortment/data/ir_cron.xml
odoo/addons/product_assortment/i18n/ca.po
odoo/addons/product_assortment/i18n/de.po
odoo/addons/product_assortment/i18n/es.po
odoo/addons/product_assortment/i18n/fr.po
odoo/addons/product_assortment/i18n/it.po
odoo/addons/product_assortment/i18n/nl.po
odoo/addons/product_assortment/i18n/product_assortment.pot
odoo/addons/product_assortment/migrations/18.0.1.0.0/pre-migrate.py
odoo/addons/product_assortment/models/__init__.py
odoo/addons/product_assortment/models/ir_filters.py
odoo/addons/product_assortment/models/res_partner.py
odoo/addons/product_assortment/readme/CONTRIBUTORS.md
odoo/addons/product_assortment/readme/DESCRIPTION.md
odoo/addons/product_assortment/readme/HISTORY.md
odoo/addons/product_assortment/readme/USAGE.md
odoo/addons/product_assortment/security/product_assortment_security.xml
odoo/addons/product_assortment/static/description/icon.png
odoo/addons/product_assortment/static/description/index.html
odoo/addons/product_assortment/tests/__init__.py
odoo/addons/product_assortment/tests/test_product_assortment.py
odoo/addons/product_assortment/views/product_assortment.xml
odoo/addons/product_assortment/views/res_partner_view.xml
odoo_addon_product_assortment-18.0.1.0.1.dist-info/METADATA
odoo_addon_product_assortment-18.0.1.0.1.dist-info/WHEEL
odoo_addon_product_assortment-18.0.1.0.1.dist-info/top_level.txt
odoo_addon_product_assortment-18.0.1.0.1.dist-info/RECORD
